Workbook

Sheet Three Statement Model
B1: Historical | G1: Forecast
B2: 2020 | C2: 2021 | D2: 2022 | E2: 2023 | F2: 2024 | G2: 2025 | H2: 2026 | I2: 2027 | J2: 2028 | K2: 2029
A3: =IF(L32=0,"OK","NOT BALANCED") -> OK | B3: -5 | C3: -4 | D3: -3 | E3: -2 | F3: -1 | G3: 1 | H3: =G3+1 -> 2 | I3: =H3+1 -> 3 | J3: =I3+1 -> 4 | K3: =J3+1 -> 5
A4: ($ in millions) | F4: CASE: | G4: 2 | H4: =CHOOSE(G4,"BEAR","BASE","BULL") -> BASE
A5: BALANCE SHEET
A6: Assets
A7: Cash and Cash Equivalents | B7: 19384 | C7: 17576 | D7: 16253 | E7: 16398 | F7: 16139 | G7: =G132 -> 18196.17 | H7: =H132 -> 20124.579 | I7: =I132 -> 22210.089 | J7: =J132 -> 24097.233 | K7: =K132 -> 25986.212
A8: EXCESS CASH | G8: =IF(G92>0,G92,0) -> 0 | H8: =IF(H92>0,H92,0) -> 0 | I8: =IF(I92>0,I92,0) -> 0 | J8: =IF(J92>0,J92,0) -> 0 | K8: =IF(K92>0,K92,0) -> 0
A9: Short-term Investments | B9: 0 | C9: 131 | D9: 5932 | E9: 12696 | F9: 20424 | G9: =G133 -> 16055.444 | H9: =H133 -> 17756.981 | I9: =I133 -> 19597.137 | J9: =J133 -> 21262.264 | K9: =K133 -> 22929.011
A10: Accounts Receivable, net | B10: 1886 | C10: 1913 | D10: 2952 | E10: 3508 | F10: 4418 | G10: =G134 -> 4388.4881 | H10: =H134 -> 4853.5748 | I10: =I134 -> 5356.5508 | J10: =J134 -> 5811.6855 | K10: =K134 -> 6267.2629
A11: Inventory | B11: 4101 | C11: 5757 | D11: 12839 | E11: 13626 | F11: 12017 | G11: =G135 -> 16186.521 | H11: =H135 -> 17752.967 | I11: =I135 -> 19172.289 | J11: =J135 -> 20410.623 | K11: =K135 -> 21646.359
A12: Prepaid Expenses | B12: 1346 | C12: 1723 | D12: 2941 | E12: 3388 | F12: 5362 | G12: =G136 -> 4281.4518 | H12: =H136 -> 4735.195 | I12: =I136 -> 5225.9032 | J12: =J136 -> 5669.9371 | K12: =K136 -> 6114.4028
A13: PP&E, net | B13: 12747 | C13: 18884 | D13: 23548 | E13: 29725 | F13: 35836 | G13: =G37 -> 40652.633 | H13: =H37 -> 45979.728 | I13: =I37 -> 51858.869 | J13: =J37 -> 58237.548 | K13: =K37 -> 65116.251
A14: Goodwill | B14: 207 | C14: 200 | D14: 194 | E14: 253 | F14: 244 | G14: 244 | H14: 244 | I14: 244 | J14: 244 | K14: 244
A15: Other Assets | B15: 12477 | C15: 15947 | D15: 17679 | E15: 27024 | F15: 27630 | G15: =F15 -> 27630 | H15: =G15 -> 27630 | I15: =H15 -> 27630 | J15: =I15 -> 27630 | K15: =J15 -> 27630
A16: Total Assets | B16: 52148 | C16: 62131 | D16: 82338 | E16: 106618 | F16: 122070 | G16: =SUM(G7:G15) -> 127634.71 | H16: =SUM(H7:H15) -> 139077.02 | I16: =SUM(I7:I15) -> 151294.84 | J16: =SUM(J7:J15) -> 163363.29 | K16: =SUM(K7:K15) -> 175933.5
A18: Liabilities
A19: A/P & Accrued Liabilities | B19: 10658 | C19: 16669 | D19: 23460 | E19: 23511 | F19: 23197 | G19: =G138 -> 27123.36 | H19: =H138 -> 29748.215 | I19: =I138 -> 32126.539 | J19: =J138 -> 34201.584 | K19: =K138 -> 36272.277
A20: Deferred Revenue | B20: 1458 | C20: 1447 | D20: 1747 | E20: 2864 | F20: 3168 | G20: =G139 -> 3211.0889 | H20: =H139 -> 3551.3962 | I20: =I139 -> 3919.4274 | J20: =J139 -> 4252.4528 | K20: =K139 -> 4585.8021
A21: NEW Revolver | G21: =-IF(G92<0,G92,0) -> 349.67602 | H21: =-IF(H92<0,H92,0) -> 6959.2964 | I21: =-IF(I92<0,I92,0) -> 8667.4409 | J21: =-IF(J92<0,J92,0) -> 7829.3779 | K21: =-IF(K92<0,K92,0) -> 4923.6753
A22: Debt | B22: 11739 | C22: 6834 | D22: 3099 | E22: 5230 | F22: 8213 | G22: =G142 -> 5860 | H22: =H142 -> 1744 | I22: =I142 -> 1045 | J22: =J142 -> 802 | K22: =K142 -> 707
A23: Other Liabilities | B23: 4614 | C23: 5598 | D23: 8134 | E23: 11404 | F23: 13812 | G23: =G140 -> 13979.271 | H23: =H140 -> 15352.06 | I23: =I140 -> 16636.203 | J23: =J140 -> 17764.644 | K23: =K140 -> 18891.408
A24: Total Liabilities | B24: =SUM(B19:B23) -> 28469 | C24: =SUM(C19:C23) -> 30548 | D24: =SUM(D19:D23) -> 36440 | E24: =SUM(E19:E23) -> 43009 | F24: =SUM(F19:F23) -> 48390 | G24: =SUM(G19:G23) -> 50523.395 | H24: =SUM(H19:H23) -> 57354.968 | I24: =SUM(I19:I23) -> 62394.61 | ... K24: =SUM(K19:K23) -> 65380.163
A25: Shareholder's Equity
A26: Paid-in Capital | B26: 27261 | C26: 29804 | D26: 32180 | E26: 34895 | F26: 38374 | G26: =F26 -> 38374 | H26: =G26 -> 38374 | I26: =H26 -> 38374 | J26: =I26 -> 38374 | K26: =J26 -> 38374
A27: Other Equity | B27: 363 | C27: 54 | D27: -361 | E27: -143 | F27: -670 | G27: =F27 -> -670 | H27: =G27 -> -670 | I27: =H27 -> -670 | J27: =I27 -> -670 | K27: =J27 -> -670
A28: Retained Earnings | B28: -5399 | C28: 331 | D28: 12885 | E28: 27882 | F28: 35209 | G28: =G59 -> 38640.313 | H28: =H59 -> 43251.056 | I28: =I59 -> 50429.228 | J28: =J59 -> 60042.231 | K28: =K59 -> 72082.335
A29: Noncontrolling Interests | B29: 1454 | C29: 1394 | D29: 1194 | E29: 975 | F29: 767 | G29: =F29 -> 767 | H29: =G29 -> 767 | I29: =H29 -> 767 | J29: =I29 -> 767 | K29: =J29 -> 767
A30: Shareholder's Equity | B30: =SUM(B26:B29) -> 23679 | C30: =SUM(C26:C29) -> 31583 | D30: =SUM(D26:D29) -> 45898 | E30: =SUM(E26:E29) -> 63609 | F30: =SUM(F26:F29) -> 73680 | G30: =SUM(G26:G29) -> 77111.313 | H30: =SUM(H26:H29) -> 81722.056 | I30: =SUM(I26:I29) -> 88900.228 | ... K30: =SUM(K26:K29) -> 110553.34
A31: Total Liabilities and Shareholder's Equity | B31: =B24+B30 -> 52148 | C31: =C24+C30 -> 62131 | D31: =D24+D30 -> 82338 | E31: =E24+E30 -> 106618 | F31: =F24+F30 -> 122070 | G31: =G24+G30 -> 127634.71 | H31: =H24+H30 -> 139077.02 | I31: =I24+I30 -> 151294.84 | ... K31: =K24+K30 -> 175933.5
A32: Check | B32: 0 | C32: 0 | D32: 0 | E32: 0 | F32: 0 | H32: =H16-H31 -> 0 | I32: =I16-I31 -> 0 | J32: =J16-J31 -> 0 | K32: =K16-K31 -> 0 | L32: =SUM(B32:K32) -> 0
A34: Beginning PP&E | G34: =F37 -> 35836 | H34: =G37 -> 40652.633 | I34: =H37 -> 45979.728 | J34: =I37 -> 51858.869 | K34: =J37 -> 58237.548
A35: + Capex | G35: =+G143 -> 10703.63 | H35: =+H143 -> 11837.987 | I35: =+I143 -> 13064.758 | J35: =+J143 -> 14174.843 | K35: =+K143 -> 15286.007
A36: - D&A | G36: =G126 -> 5886.9962 | H36: =H126 -> 6510.8931 | I36: =I126 -> 7185.6169 | J36: =J126 -> 7796.1635 | K36: =K126 -> 8407.3039
A37: Ending PP&E | F37: =F13 -> 35836 | G37: =G34+G35-G36 -> 40652.633 | H37: =H34+H35-H36 -> 45979.728 | I37: =I34+I35-I36 -> 51858.869 | J37: =J34+J35-J36 -> 58237.548 | K37: =K34+K35-K36 -> 65116.251
A39: INCOME STATEMENT
A40: Revenues | B40: 31536 | C40: 53823 | D40: 81462 | E40: 96773 | F40: 97690 | G40: =G124 -> 107036.3 | H40: =H124 -> 118379.87 | I40: =I124 -> 130647.58 | J40: =J124 -> 141748.43 | K40: =K124 -> 152860.07
A41: Cost of Goods Sold | B41: 22584 | C41: 37306 | D41: 56862 | E41: 74446 | F41: 74872 | G41: =G125 -> 87494.709 | H41: =H125 -> 95961.984 | I41: =I125 -> 103634 | J41: =J125 -> 110327.69 | K41: =K125 -> 117007.35
A42: Gross profit | B42: 8952 | C42: 16517 | D42: 24600 | E42: 22327 | F42: 22818 | G42: =G40-G41 -> 19541.586 | H42: =H40-H41 -> 22417.891 | I42: =I40-I41 -> 27013.584 | J42: =J40-J41 -> 31420.735 | K42: =K40-K41 -> 35852.724
A43: R&D | B43: 1491 | C43: 2593 | D43: 3075 | E43: 3969 | F43: 4540 | G43: =G127 -> 4816.6333 | H43: =H127 -> 5327.0943 | I43: =I127 -> 5879.1411 | J43: =J127 -> 6378.6792 | K43: =K127 -> 6878.7032
A44: SG&A | B44: 3145 | C44: 4517 | D44: 3946 | E44: 4800 | F44: 5150 | G44: =G128 -> 5351.8148 | H44: =H128 -> 5918.9937 | I44: =I128 -> 6532.379 | J44: =J128 -> 7087.4214 | K44: =K128 -> 7643.0035
A45: EBITDA | B45: 4316 | C45: 9407 | D45: 17579 | E45: 13558 | F45: 13128 | G45: =G42-G43-G44 -> 9373.1382 | H45: =H42-H43-H44 -> 11171.803 | I45: =I42-I43-I44 -> 14602.064 | J45: =J42-J43-J44 -> 17954.635 | K45: =K42-K43-K44 -> 21331.018
A46: D&A | B46: 2322 | C46: 2911 | D46: 3747 | E46: 4667 | F46: 5368 | G46: =G126 -> 5886.9962 | H46: =H126 -> 6510.8931 | I46: =I126 -> 7185.6169 | J46: =J126 -> 7796.1635 | K46: =K126 -> 8407.3039
A47: Other Opex | B47: 0 | C47: -27 | D47: 176 | E47: 0 | F47: 684
A48: Operating Income | B48: 1994 | C48: 6523 | D48: 13656 | E48: 8891 | F48: 7076 | G48: =G45-G46-G47 -> 3486.142 | H48: =H45-H46-H47 -> 4660.9095 | I48: =I45-I46-I47 -> 7416.4473 | J48: =J45-J46-J47 -> 10158.471 | K48: =K45-K46-K47 -> 12923.714
A49: Interest Income | B49: 30 | C49: 56 | D49: 297 | E49: 1066 | F49: 1569 | G49: =G129 -> 968.34 | H49: =H129 -> 1091.7702 | I49: =I129 -> 1207.4747 | J49: =J129 -> 1332.6053 | K49: =K129 -> 1445.834
A50: Interest Expense | B50: -748 | C50: -371 | D50: -191 | E50: -156 | F50: -350 | G50: =-G130 -> -369.585 | H50: =-H130 -> -263.7 | I50: =-I130 -> -78.48 | J50: =-J130 -> -47.025 | K50: =-K130 -> -36.09
A51: Other | B51: -122 | C51: 135 | D51: -43 | E51: 172 | F51: 695
A52: Pre-Tax Income | B52: 1154 | C52: 6343 | D52: 13719 | E52: 9973 | F52: 8990 | G52: =SUM(G48:G51) -> 4084.897 | H52: =SUM(H48:H51) -> 5488.9797 | I52: =SUM(I48:I51) -> 8545.442 | J52: =SUM(J48:J51) -> 11444.052 | K52: =SUM(K48:K51) -> 14333.458
A53: Taxes | B53: 292 | C53: 699 | D53: 1132 | E53: -5001 | F53: 1837 | G53: =G160*G52 -> 653.58351 | H53: =H160*H52 -> 878.23675 | I53: =I160*I52 -> 1367.2707 | J53: =J160*J52 -> 1831.0483 | K53: =K160*K52 -> 2293.3532
A54: Net Income | B54: 862 | C54: 5644 | D54: 12587 | E54: 14974 | F54: 7153 | G54: =G52-G53 -> 3431.3134 | H54: =H52-H53 -> 4610.7429 | I54: =I52-I53 -> 7178.1713 | J54: =J52-J53 -> 9613.0034 | K54: =K52-K53 -> 12040.104
A56: Beginning Retained Earnings | G56: =F59 -> 35209 | H56: =G59 -> 38640.313 | I56: =H59 -> 43251.056 | J56: =I59 -> 50429.228 | K56: =J59 -> 60042.231
A57: + Net Income | G57: =G54 -> 3431.3134 | H57: =H54 -> 4610.7429 | I57: =I54 -> 7178.1713 | J57: =J54 -> 9613.0034 | K57: =K54 -> 12040.104
A58: - Dividends | G58: 0 | H58: 0 | I58: 0 | J58: 0 | K58: 0
A59: Ending Retained Earnings | F59: =F28 -> 35209 | G59: =G56+G57-G58 -> 38640.313 | H59: =H56+H57-H58 -> 43251.056 | I59: =I56+I57-I58 -> 50429.228 | J59: =J56+J57-J58 -> 60042.231 | K59: =K56+K57-K58 -> 72082.335
A61: CASH FLOW STATEMENT
A62: Operating Cash Flow
A63: Net income | B63: 862 | C63: 5644 | D63: 12587 | E63: 14974 | F63: 7153 | G63: =G54 -> 3431.3134 | H63: =H54 -> 4610.7429 | I63: =I54 -> 7178.1713 | J63: =J54 -> 9613.0034 | K63: =K54 -> 12040.104
A64: D&A | B64: 2322 | C64: 2911 | D64: 3747 | E64: 4667 | F64: 5368 | G64: =G126 -> 5886.9962 | H64: =H126 -> 6510.8931 | I64: =I126 -> 7185.6169 | J64: =J126 -> 7796.1635 | K64: =K126 -> 8407.3039
A65: Other non-cash charges | B65: 2575 | C65: 2424 | D65: 2102 | E65: -4137 | F65: 2321
A66: 𝚫 in Accounts Receivables | B66: -652 | C66: -130 | D66: -1124 | E66: -586 | F66: -1083 | G66: =-(G10-F10) -> 29.511905 | H66: =-(H10-G10) -> -465.08675 | I66: =-(I10-H10) -> -502.97595 | J66: =-(J10-I10) -> -455.13471 | K66: =-(K10-J10) -> -455.57738
A67: 𝚫 in Inventory | B67: -422 | C67: -1709 | D67: -6465 | E67: -1195 | F67: 937 | G67: =-(G11-F11) -> -4169.5211 | H67: =-(H11-G11) -> -1566.4458 | I67: =-(I11-H11) -> -1419.3223 | J67: =-(J11-I11) -> -1238.3337 | K67: =-(K11-J11) -> -1235.7361
A68: 𝚫 in Prepaid expenses | B68: -595 | C68: -1562 | D68: -3713 | E68: -2652 | F68: -3273 | G68: =-(G12-F12) -> 1080.5482 | H68: =-(H12-G12) -> -453.74317 | I68: =-(I12-H12) -> -490.70825 | J68: =-(J12-I12) -> -444.03387 | K68: =-(K12-J12) -> -444.46574
A69: 𝚫 in A/P & Accrued Liabilities | B69: 2604 | C69: 5240 | D69: 8029 | E69: 2605 | F69: 3588 | G69: =G19-F19 -> 3926.3597 | H69: =H19-G19 -> 2624.8552 | I69: =I19-H19 -> 2378.3239 | J69: =J19-I19 -> 2075.0456 | K69: =K19-J19 -> 2070.6929
A70: Other Changes in OWC | B70: -751 | C70: -1321 | D70: -439 | E70: -420 | F70: -88 | G70: =(G20-F20)+(G23-F23) -> 210.35951 | H70: =(H20-G20)+(H23-G23) -> 1713.0969 | I70: =(I20-H20)+(I23-H23) -> 1652.1739 | J70: =(J20-I20)+(J23-I23) -> 1461.4664 | K70: =(K20-J20)+(K23-J23) -> 1460.1135
A71: Net cash from operations | B71: 5943 | C71: 11497 | D71: 14724 | E71: 13256 | F71: 14923 | G71: =SUM(G63:G70) -> 10395.568 | H71: =SUM(H63:H70) -> 12974.312 | I71: =SUM(I63:I70) -> 15981.279 | J71: =SUM(J63:J70) -> 18808.177 | K71: =SUM(K63:K70) -> 21842.435
A73: Investing Cash Flow
A74: Capex | B74: -3157 | C74: -6482 | D74: -7158 | E74: -8898 | F74: -11339 | G74: =-G143 -> -10703.63 | H74: =-H143 -> -11837.987 | I74: =-I143 -> -13064.758 | J74: =-J143 -> -14174.843 | K74: =-K143 -> -15286.007
A75: Other cash from investing | B75: 25 | C75: -1386 | D75: -4815 | E75: -6686 | F75: -7448 | G75: =-(G9-F9) -> 4368.5557 | H75: =-(H9-G9) -> -1701.5369 | I75: =-(I9-H9) -> -1840.1559 | J75: =-(J9-I9) -> -1665.127 | K75: =-(K9-J9) -> -1666.7465
A76: Net cash from investing | B76: -3132 | C76: -7868 | D76: -11973 | E76: -15584 | F76: -18787 | G76: =SUM(G74:G75) -> -6335.0738 | H76: =SUM(H74:H75) -> -13539.524 | I76: =SUM(I74:I75) -> -14904.914 | J76: =SUM(J74:J75) -> -15839.97 | K76: =SUM(K74:K75) -> -16952.754
A78: Financing Cash Flow
A79: Equity issuance | B79: 12269 | C79: 0 | D79: 0 | E79: 0 | F79: 0
A80: Debt issuance | B80: 9713 | C80: 8883 | D80: 0 | E80: 3931 | F80: 5744
A81: Debt repayment | B81: -12201 | C81: -14615 | D81: -3866 | E81: -1815 | F81: -2881 | G81: =G22-F22 -> -2353 | H81: =H22-G22 -> -4116 | I81: =I22-H22 -> -699 | J81: =J22-I22 -> -243 | K81: =K22-J22 -> -95
A82: Other cash from financing | B82: 192 | C82: 529 | D82: 339 | E82: 473 | F82: 990
A83: Net cash from financing | B83: 9973 | C83: -5203 | D83: -3527 | E83: 2589 | F83: 3853 | G83: =SUM(G79:G82) -> -2353 | H83: =SUM(H79:H82) -> -4116 | I83: =SUM(I79:I82) -> -699 | J83: =SUM(J79:J82) -> -243 | K83: =SUM(K79:K82) -> -95
A84: FX impact | B84: 334 | C84: -183 | D84: -444 | E84: 4 | F84: -141
A86: Net change in cash for the period | B86: 13118 | C86: -1757 | D86: -1220 | E86: 265 | F86: -152 | G86: =G71+G76+G83 -> 1707.4941 | H86: =H71+H76+H83 -> -4681.2119 | I86: =I71+I76+I83 -> 377.3655 | J86: =J71+J76+J83 -> 2725.207 | K86: =K71+K76+K83 -> 4794.6819
A88: Opening Cash | B88: 6783 | C88: 19901 | D88: 18144 | E88: 16924 | F88: 17189 | G88: =F90 -> 16139 | H88: =G90 -> 17846.494 | I88: =H90 -> 13165.282 | J88: =I90 -> 13542.648 | K88: =J90 -> 16267.855
A89: Net change in cash for the period | B89: 13118 | C89: -1757 | D89: -1220 | E89: 265 | F89: -152 | G89: =G86 -> 1707.4941 | H89: =H86 -> -4681.2119 | I89: =I86 -> 377.3655 | J89: =J86 -> 2725.207 | K89: =K86 -> 4794.6819
A90: Closing Cash | B90: 19901 | C90: 18144 | D90: 16924 | E90: 17189 | F90: =F7 -> 16139 | G90: =SUM(G88:G89) -> 17846.494 | H90: =SUM(H88:H89) -> 13165.282 | I90: =SUM(I88:I89) -> 13542.648 | J90: =SUM(J88:J89) -> 16267.855 | K90: =SUM(K88:K89) -> 21062.537
A91: Required Cash | G91: =G7 -> 18196.17 | H91: =H7 -> 20124.579 | I91: =I7 -> 22210.089 | J91: =J7 -> 24097.233 | K91: =K7 -> 25986.212
A92: EXCESS Cash / (Revolver) | G92: =G90-G91 -> -349.67602 | H92: =H90-H91 -> -6959.2964 | I92: =I90-I91 -> -8667.4409 | J92: =J90-J91 -> -7829.3779 | K92: =K90-K91 -> -4923.6753
A94: REVENUE&COGS BREAKDOWN
A95: INCOME STATEMENT
A96: Automotive | B96: 27236 | C96: 47232 | D96: 71462 | E96: 82419 | F96: 77070 | G96: =G108*G110 -> 79266.495 | H96: =H108*H110 -> 83039.58 | I96: =I108*I110 -> 87963.827 | J96: =J108*J110 -> 91900.209 | K96: =K108*K110 -> 96495.219
A97: Energy Generation and Storage | B97: 1994 | C97: 2789 | D97: 3909 | E97: 6035 | F97: 10086 | G97: =F97*(1+G116) -> 15129 | H97: =G97*(1+H116) -> 20424.15 | I97: =H97*(1+I116) -> 25530.188 | J97: =I97*(1+J116) -> 30636.225 | K97: =J97*(1+K116) -> 35231.659
A98: Services and Other | B98: 2306 | C98: 3802 | D98: 6091 | E98: 8319 | F98: 10534 | G98: =F98*(1+G120) -> 12640.8 | H98: =G98*(1+H120) -> 14916.144 | I98: =H98*(1+I120) -> 17153.566 | J98: =I98*(1+J120) -> 19211.993 | K98: =J98*(1+K120) -> 21133.193
A99: Total Revenue | B99: =SUM(B96:B98) -> 31536 | C99: =SUM(C96:C98) -> 53823 | D99: =SUM(D96:D98) -> 81462 | E99: =SUM(E96:E98) -> 96773 | F99: =SUM(F96:F98) -> 97690 | G99: =SUM(G96:G98) -> 107036.3 | H99: =SUM(H96:H98) -> 118379.87 | I99: =SUM(I96:I98) -> 130647.58 | ... K99: =SUM(K96:K98) -> 152860.07
A101: Cost of Automotive | B101: 20259 | C101: 33393 | D101: 51108 | E101: 66389 | F101: 62873 | G101: =G108*G112 -> 67500.453 | H101: =H108*H112 -> 71223.778 | I101: =I108*I112 -> 74609.044 | J101: =J108*J112 -> 76929.385 | K101: =K108*K112 -> 79806.544
A102: Cost of Energy Generation and Storage | B102: 1976 | C102: 2918 | D102: 3621 | E102: 4894 | F102: 7446 | G102: =G97*(1-G117) -> 10892.88 | H102: =H97*(1-H117) -> 14296.905 | I102: =I97*(1-I117) -> 17360.528 | J102: =J97*(1-J117) -> 20526.271 | K102: =K97*(1-K117) -> 23252.895
A103: Cost of Services and Other | B103: 2671 | C103: 3906 | D103: 5880 | E103: 7830 | F103: 9921 | G103: =G98*(1-G117) -> 9101.376 | H103: =H98*(1-H117) -> 10441.301 | I103: =I98*(1-I117) -> 11664.425 | J103: =J98*(1-J117) -> 12872.036 | K103: =K98*(1-K117) -> 13947.907
A104: Cost of Goods Sold (COGS) | B104: =SUM(B101:B103) -> 24906 | C104: =SUM(C101:C103) -> 40217 | D104: =SUM(D101:D103) -> 60609 | E104: =SUM(E101:E103) -> 79113 | F104: =SUM(F101:F103) -> 80240 | G104: =SUM(G101:G103) -> 87494.709 | H104: =SUM(H101:H103) -> 95961.984 | I104: =SUM(I101:I103) -> 103634 | ... K104: =SUM(K101:K103) -> 117007.35
A106: DRIVERS
A107: Automotive
A108: Vehicle Deliveries | B108: 499647 | C108: 936222 | D108: 1313851 | E108: 1808581 | F108: 1789266 | G108: =F108*(1+G109) -> 1968192.6 | H108: =G108*(1+H109) -> 2125648 | I108: =H108*(1+I109) -> 2274443.4 | J108: =I108*(1+J109) -> 2388165.5 | K108: =J108*(1+K109) -> 2507573.8
A109: Delivery Growth % | C109: =C108/B108-1 -> 0.87376688 | D109: =D108/C108-1 -> 0.40335412 | E109: =E108/D108-1 -> 0.37654955 | F109: =F108/E108-1 -> -0.010679643 | G109: =G148 -> 0.1 | H109: =H148 -> 0.08 | I109: =I148 -> 0.07 | J109: =J148 -> 0.05 | K109: =K148 -> 0.05
A110: Average Selling Price ($M) | B110: =B96/B108 -> 0.054510484 | C110: =C96/C108 -> 0.050449573 | D110: =D96/D108 -> 0.054391251 | E110: =E96/E108 -> 0.045571086 | F110: =F96/F108 -> 0.043073528 | G110: =F110*(1+G111) -> 0.040273749 | H110: =G110*(1+H111) -> 0.039065537 | I110: =H110*(1+I111) -> 0.038674881 | J110: =I110*(1+J111) -> 0.038481507 | K110: =J110*(1+K111) -> 0.038481507
A111: ASP Change % | C111: =C110/B110-1 -> -0.074497807 | D111: =D110/C110-1 -> 0.078131058 | E111: =E110/D110-1 -> -0.16216147 | F111: =F110/E110-1 -> -0.054805746 | G111: -0.065 | H111: -0.03 | I111: -0.01 | J111: -0.005 | K111: 0
A112: Average Cost per Vehicle ($M) | B112: =B101/B108 -> 0.040546626 | C112: =C101/C108 -> 0.035667822 | D112: =D101/D108 -> 0.038899388 | E112: =E101/E108 -> 0.036707784 | F112: =F101/F108 -> 0.03513899 | G112: =F112*(1+G113) -> 0.034295654 | H112: =G112*(1+H113) -> 0.033506854 | I112: =H112*(1+I113) -> 0.03280321 | J112: =I112*(1+J113) -> 0.032212752 | K112: =J112*(1+K113) -> 0.031826199
...

Sheet Charts and Graphs
A1: CHART AND GRAPHS | B1: Historical | G1: Forecast
A2: ($ in millions) | B2: 44196 | C2: 44561 | D2: 44926 | E2: 45291 | F2: 45657 | G2: 46022 | H2: 46387 | I2: 46752 | J2: 47118 | K2: 47483
A4: Revenue | B4: ='Three Statement Model'!B40 -> 31536 | C4: ='Three Statement Model'!C40 -> 53823 | D4: ='Three Statement Model'!D40 -> 81462 | E4: ='Three Statement Model'!E40 -> 96773 | F4: ='Three Statement Model'!F40 -> 97690 | G4: ='Three Statement Model'!G40 -> 107036.3 | H4: ='Three Statement Model'!H40 -> 118379.87 | I4: ='Three Statement Model'!I40 -> 130647.58 | ... K4: ='Three Statement Model'!K40 -> 152860.07
A5: Gross Profit Margin (%) | B5: ='Three Statement Model'!B42/'Three Statement Model'!B40 -> 0.28386606 | C5: ='Three Statement Model'!C42/'Three Statement Model'!C40 -> 0.30687624 | D5: ='Three Statement Model'!D42/'Three Statement Model'!D40 -> 0.30198129 | E5: ='Three Statement Model'!E42/'Three Statement Model'!E40 -> 0.23071518 | F5: ='Three Statement Model'!F42/'Three Statement Model'!F40 -> 0.2335756 | G5: ='Three Statement Model'!G42/'Three Statement Model'!G40 -> 0.18256972 | H5: ='Three Statement Model'!H42/'Three Statement Model'!H40 -> 0.18937248 | I5: ='Three Statement Model'!I42/'Three Statement Model'!I40 -> 0.20676682 | ... K5: ='Three Statement Model'!K42/'Three Statement Model'!K40 -> 0.23454604
A7: Operating Cash Flow | B7: ='Three Statement Model'!B71 -> 5943 | C7: ='Three Statement Model'!C71 -> 11497 | D7: ='Three Statement Model'!D71 -> 14724 | E7: ='Three Statement Model'!E71 -> 13256 | F7: ='Three Statement Model'!F71 -> 14923 | G7: ='Three Statement Model'!G71 -> 10395.568 | H7: ='Three Statement Model'!H71 -> 12974.312 | I7: ='Three Statement Model'!I71 -> 15981.279 | ... K7: ='Three Statement Model'!K71 -> 21842.435
A8: Investing Cash Flow | B8: ='Three Statement Model'!B76 -> -3132 | C8: ='Three Statement Model'!C76 -> -7868 | D8: ='Three Statement Model'!D76 -> -11973 | E8: ='Three Statement Model'!E76 -> -15584 | F8: ='Three Statement Model'!F76 -> -18787 | G8: ='Three Statement Model'!G76 -> -6335.0738 | H8: ='Three Statement Model'!H76 -> -13539.524 | I8: ='Three Statement Model'!I76 -> -14904.914 | ... K8: ='Three Statement Model'!K76 -> -16952.754
A9: Financing Cash Flow | B9: ='Three Statement Model'!B83 -> 9973 | C9: ='Three Statement Model'!C83 -> -5203 | D9: ='Three Statement Model'!D83 -> -3527 | E9: ='Three Statement Model'!E83 -> 2589 | F9: ='Three Statement Model'!F83 -> 3853 | G9: ='Three Statement Model'!G83 -> -2353 | H9: ='Three Statement Model'!H83 -> -4116 | I9: ='Three Statement Model'!I83 -> -699 | ... K9: ='Three Statement Model'!K83 -> -95

Sheet Rev&COGS breakdown
A1: REVENUE&COGS BREAKDOWN
A2: INCOME STATEMENT
A3: Automotive | B3: 27236 | C3: 47232 | D3: 71462 | E3: 82419 | F3: 77070 | G3: =G15*G17 -> 79266.495 | H3: =H15*H17 -> 83039.58 | I3: =I15*I17 -> 87963.827 | J3: =J15*J17 -> 91900.209 | K3: =K15*K17 -> 96495.219
A4: Energy Generation and Storage | B4: 1994 | C4: 2789 | D4: 3909 | E4: 6035 | F4: 10086 | G4: =F4*(1+G23) -> 15129 | H4: =G4*(1+H23) -> 20424.15 | I4: =H4*(1+I23) -> 25530.188 | J4: =I4*(1+J23) -> 30636.225 | K4: =J4*(1+K23) -> 35231.659
A5: Services and Other | B5: 2306 | C5: 3802 | D5: 6091 | E5: 8319 | F5: 10534 | G5: =F5*(1+G27) -> 12640.8 | H5: =G5*(1+H27) -> 14916.144 | I5: =H5*(1+I27) -> 17153.566 | J5: =I5*(1+J27) -> 19211.993 | K5: =J5*(1+K27) -> 21133.193
A6: Total Revenue | B6: =SUM(B3:B5) -> 31536 | C6: =SUM(C3:C5) -> 53823 | D6: =SUM(D3:D5) -> 81462 | E6: =SUM(E3:E5) -> 96773 | F6: =SUM(F3:F5) -> 97690 | G6: =SUM(G3:G5) -> 107036.3 | H6: =SUM(H3:H5) -> 118379.87 | I6: =SUM(I3:I5) -> 130647.58 | ... K6: =SUM(K3:K5) -> 152860.07
A8: Cost of Automotive | B8: 20259 | C8: 33393 | D8: 51108 | E8: 66389 | F8: 62873 | G8: =G15*G19 -> 67500.453 | H8: =H15*H19 -> 71223.778 | I8: =I15*I19 -> 74609.044 | J8: =J15*J19 -> 76929.385 | K8: =K15*K19 -> 79806.544
A9: Cost of Energy Generation and Storage | B9: 1976 | C9: 2918 | D9: 3621 | E9: 4894 | F9: 7446 | G9: =G4*(1-G24) -> 10892.88 | H9: =H4*(1-H24) -> 14296.905 | I9: =I4*(1-I24) -> 17360.528 | J9: =J4*(1-J24) -> 20526.271 | K9: =K4*(1-K24) -> 23252.895
A10: Cost of Services and Other | B10: 2671 | C10: 3906 | D10: 5880 | E10: 7830 | F10: 9921 | G10: =G5*(1-G24) -> 9101.376 | H10: =H5*(1-H24) -> 10441.301 | I10: =I5*(1-I24) -> 11664.425 | J10: =J5*(1-J24) -> 12872.036 | K10: =K5*(1-K24) -> 13947.907
A11: Cost of Goods Sold (COGS) | B11: =SUM(B8:B10) -> 24906 | C11: =SUM(C8:C10) -> 40217 | D11: =SUM(D8:D10) -> 60609 | E11: =SUM(E8:E10) -> 79113 | F11: =SUM(F8:F10) -> 80240 | G11: =SUM(G8:G10) -> 87494.709 | H11: =SUM(H8:H10) -> 95961.984 | I11: =SUM(I8:I10) -> 103634 | ... K11: =SUM(K8:K10) -> 117007.35
A13: DRIVERS
A14: Automotive
A15: Vehicle Deliveries | B15: 499647 | C15: 936222 | D15: 1313851 | E15: 1808581 | F15: 1789266 | G15: =F15*(1+G16) -> 1968192.6 | H15: =G15*(1+H16) -> 2125648 | I15: =H15*(1+I16) -> 2274443.4 | J15: =I15*(1+J16) -> 2388165.5 | K15: =J15*(1+K16) -> 2507573.8
A16: Delivery Growth % | C16: =C15/B15-1 -> 0.87376688 | D16: =D15/C15-1 -> 0.40335412 | E16: =E15/D15-1 -> 0.37654955 | F16: =F15/E15-1 -> -0.010679643 | G16: 0.1 | H16: 0.08 | I16: 0.07 | J16: 0.05 | K16: 0.05
A17: Average Selling Price ($M) | B17: =B3/B15 -> 0.054510484 | C17: =C3/C15 -> 0.050449573 | D17: =D3/D15 -> 0.054391251 | E17: =E3/E15 -> 0.045571086 | F17: =F3/F15 -> 0.043073528 | G17: =F17*(1+G18) -> 0.040273749 | H17: =G17*(1+H18) -> 0.039065537 | I17: =H17*(1+I18) -> 0.038674881 | J17: =I17*(1+J18) -> 0.038481507 | K17: =J17*(1+K18) -> 0.038481507
A18: ASP Change % | C18: =C17/B17-1 -> -0.074497807 | D18: =D17/C17-1 -> 0.078131058 | E18: =E17/D17-1 -> -0.16216147 | F18: =F17/E17-1 -> -0.054805746 | G18: -0.065 | H18: -0.03 | I18: -0.01 | J18: -0.005 | K18: 0
A19: Average Cost per Vehicle ($M) | B19: =B8/B15 -> 0.040546626 | C19: =C8/C15 -> 0.035667822 | D19: =D8/D15 -> 0.038899388 | E19: =E8/E15 -> 0.036707784 | F19: =F8/F15 -> 0.03513899 | G19: =F19*(1+G20) -> 0.034295654 | H19: =G19*(1+H20) -> 0.033506854 | I19: =H19*(1+I20) -> 0.03280321 | J19: =I19*(1+J20) -> 0.032212752 | K19: =J19*(1+K20) -> 0.031826199
A20: Cost Change % | C20: =C19/B19-1 -> -0.12032576 | D20: =D19/C19-1 -> 0.090601712 | E20: =E19/D19-1 -> -0.056340334 | F20: =F19/E19-1 -> -0.042737357 | G20: -0.024 | H20: -0.023 | I20: -0.021 | J20: -0.018 | K20: -0.012
A22: Energy Generation and Storage
A23: Energy Revenue Growth % | C23: =C4/B4-1 -> 0.39869609 | D23: =D4/C4-1 -> 0.40157763 | E23: =E4/D4-1 -> 0.54387311 | F23: =F4/E4-1 -> 0.67125104 | G23: 0.5 | H23: 0.35 | I23: 0.25 | J23: 0.2 | K23: 0.15
A24: Energy Gross Margin | B24: =1-B9/B4 -> 0.0090270812 | C24: =1-C9/C4 -> -0.046253137 | D24: =1-D9/D4 -> 0.073676132 | E24: =1-E9/E4 -> 0.18906379 | F24: =1-F9/F4 -> 0.26174896 | G24: 0.28 | H24: 0.3 | I24: 0.32 | J24: 0.33 | K24: 0.34
A26: Services and Other
A27: Services and Other Growth % | C27: =C5/B5-1 -> 0.64874241 | D27: =D5/C5-1 -> 0.60205155 | E27: =E5/D5-1 -> 0.36578559 | F27: =F5/E5-1 -> 0.26625796 | G27: 0.2 | H27: 0.18 | I27: 0.15 | J27: 0.12 | K27: 0.1
A28: Services Gross Margin | B28: =1-B10/B5 -> -0.15828274 | C28: =1-C10/C5 -> -0.027354024 | D28: =1-D10/D5 -> 0.034641274 | E28: =1-E10/E5 -> 0.058781103 | F28: =1-F10/F5 -> 0.058192519 | G28: 0.06 | H28: 0.065 | I28: 0.065 | J28: 0.07 | K28: 0.07

Sheet Financials
B1: 2020 | C1: 2021 | D1: 2022 | E1: 2023 | F1: 2024
A2: BALANCE SHEET
A3: Assets | G3: BUCKET | J3: 2020 | K3: 2021 | L3: 2022 | M3: 2023 | N3: 2024
A4: Cash and cash equivalents | B4: 19384 | C4: 17576 | D4: 16253 | E4: 16398 | F4: 16139 | G4: Cash and cash equivalents | I4: Cash and cash equivalents | J4: =B4 -> 19384 | K4: =C4 -> 17576 | L4: =D4 -> 16253 | M4: =E4 -> 16398 | N4: =F4 -> 16139
A5: Short-term investments | B5: 0 | C5: 131 | D5: 5932 | E5: 12696 | F5: 20424 | G5: Short-term investments | I5: Short-term investments | J5: =B5 -> 0 | K5: =C5 -> 131 | L5: =D5 -> 5932 | M5: =E5 -> 12696 | N5: =F5 -> 20424
A6: Accounts receivable, net | B6: 1886 | C6: 1913 | D6: 2952 | E6: 3508 | F6: 4418 | G6: Accounts receivable, net | I6: Accounts receivable, net | J6: =B6 -> 1886 | K6: =C6 -> 1913 | L6: =D6 -> 2952 | M6: =E6 -> 3508 | N6: =F6 -> 4418
A7: Inventory | B7: 4101 | C7: 5757 | D7: 12839 | E7: 13626 | F7: 12017 | G7: Inventory | I7: Inventory | J7: =B7 -> 4101 | K7: =C7 -> 5757 | L7: =D7 -> 12839 | M7: =E7 -> 13626 | N7: =F7 -> 12017
A8: Prepaid expenses and other current assets | B8: 1346 | C8: 1723 | D8: 2941 | E8: 3388 | F8: 5362 | G8: Prepaid expenses | I8: Prepaid expenses | J8: =B8 -> 1346 | K8: =C8 -> 1723 | L8: =D8 -> 2941 | M8: =E8 -> 3388 | N8: =F8 -> 5362
A9: Total current assets | B9: 26717 | C9: 27100 | D9: =SUM(D4:D8) -> 40917 | E9: 49616 | F9: 58360 | I9: PP&E, net | J9: =B12 -> 12747 | K9: =C12 -> 18884 | L9: =D12 -> 23548 | M9: =E12 -> 29725 | N9: =F12 -> 35836
A10: Operating lease vehicles, net | B10: 3091 | C10: 4511 | D10: 5035 | E10: 5989 | F10: 5581 | G10: Other assets | I10: Goodwill | J10: =B16 -> 207 | K10: =C16 -> 200 | L10: =D16 -> 194 | M10: =E16 -> 253 | N10: =F16 -> 244
A11: Solar energy systems, net | B11: 5979 | C11: 5765 | D11: 5489 | E11: 5229 | F11: 4924 | G11: Other assets | I11: Other assets | J11: =B10+B11+B13+B14+B15+B17+B18 -> 12477 | K11: =C10+C11+C13+C14+C15+C17+C18 -> 15947 | L11: =D10+D11+D13+D14+D15+D17+D18 -> 17679 | M11: =E10+E11+E13+E14+E15+E17+E18 -> 27024 | N11: =F10+F11+F13+F14+F15+F17+F18 -> 27630
A12: Property, plant and equipment, net | B12: 12747 | C12: 18884 | D12: 23548 | E12: 29725 | F12: 35836 | G12: PP&E, net | I12: Total assets | J12: =SUM(J4:J11) -> 52148 | K12: =SUM(K4:K11) -> 62131 | L12: =SUM(L4:L11) -> 82338 | M12: =SUM(M4:M11) -> 106618 | N12: =SUM(N4:N11) -> 122070
A13: Operating lease right-of-use assets | B13: 1558 | C13: 2016 | D13: 2563 | E13: 4180 | F13: 5160 | G13: Other assets | I13: A/P & Accrued Liabilities | J13: =B22+B23 -> 10658 | K13: =C22+C23 -> 16669 | L13: =D22+D23 -> 23460 | M13: =E22+E23 -> 23511 | N13: =F22+F23 -> 23197
A14: Digital assets, net | B14: 0 | C14: 1260 | D14: 184 | E14: 184 | F14: 1076 | G14: Other assets | I14: Deferred revenue | J14: =B24 -> 1458 | K14: =C24 -> 1447 | L14: =D24 -> 1747 | M14: =E24 -> 2864 | N14: =F24 -> 3168
A15: Intangible assets, net | B15: 313 | C15: 257 | D15: 215 | E15: 178 | F15: 150 | G15: Other assets | I15: Debt | J15: =B25+B27+B33 -> 11739 | K15: =C25+C27+C33 -> 6834 | L15: =D25+D27+D33 -> 3099 | M15: =E25+E27+E33 -> 5230 | N15: =F25+F27+F33 -> 8213
A16: Goodwill | B16: 207 | C16: 200 | D16: 194 | E16: 253 | F16: 244 | G16: Goodwill | I16: Other liabilities | J16: =B28+B29 -> 4614 | K16: =C28+C29 -> 5598 | L16: =D28+D29 -> 8134 | M16: =E28+E29 -> 11404 | N16: =F28+F29 -> 13812
A17: Deferred tax assets | B17: 0 | C17: 0 | D17: 0 | E17: 6733 | F17: 6524 | G17: Other assets | I17: Paid in capital | J17: =B37+B38 -> 27261 | K17: =C37+C38 -> 29804 | L17: =D37+D38 -> 32180 | M17: =E37+E38 -> 34895 | N17: =F37+F38 -> 38374
A18: Other non-current assets | B18: 1536 | C18: 2138 | D18: 4193 | E18: 4531 | F18: 4215 | G18: Other assets | I18: Other equity | J18: =B39 -> 363 | K18: =C39 -> 54 | L18: =D39 -> -361 | M18: =E39 -> -143 | N18: =F39 -> -670
A19: Total assets | B19: 52148 | C19: 62131 | D19: 82338 | E19: 106618 | F19: 122070 | I19: Retained earnings | J19: =B40 -> -5399 | K19: =C40 -> 331 | L19: =D40 -> 12885 | M19: =E40 -> 27882 | N19: =F40 -> 35209
I20: Noncontrolling interests | J20: =B32+B42 -> 1454 | K20: =C32+C42 -> 1394 | L20: =D32+D42 -> 1194 | M20: =E32+E42 -> 975 | N20: =F32+F42 -> 767
A21: Liabilities | I21: Total liabilities and equity | J21: =SUM(J13:J20) -> 52148 | K21: =SUM(K13:K20) -> 62131 | L21: =SUM(L13:L20) -> 82338 | M21: =SUM(M13:M20) -> 106618 | N21: =SUM(N13:N20) -> 122070
A22: Accounts payable | B22: 6051 | C22: 10025 | D22: 15255 | E22: 14431 | F22: 12474 | G22: A/P & Accrued Liabilities | I22: Check | J22: =J12-J21 -> 0 | K22: =K12-K21 -> 0 | L22: =L12-L21 -> 0 | M22: =M12-M21 -> 0 | N22: =N12-N21 -> 0
A23: Accrued liabilities and other | B23: =3855+752 -> 4607 | C23: =5719+925 -> 6644 | D23: =7142+1063 -> 8205 | E23: 9080 | F23: 10723 | G23: A/P & Accrued Liabilities
A24: Deferred revenue | B24: 1458 | C24: 1447 | D24: 1747 | E24: 2864 | F24: 3168 | G24: Deferred revenue
A25: Current portion of debt and finance leases | B25: 2132 | C25: 1589 | D25: 1502 | E25: 2373 | F25: 2456 | G25: Debt
A26: Total current liabilities | B26: 14248 | C26: 19705 | D26: =SUM(D22:D25) -> 26709 | E26: 28748 | F26: 28821
A27: Debt and finance leases, net of current portion | B27: 9556 | C27: 5245 | D27: 1597 | E27: 2857 | F27: 5757 | G27: Debt
A28: Deferred revenue, net of current portion | B28: 1284 | C28: 2052 | D28: 2804 | E28: 3251 | F28: 3317 | G28: Other liabilities
A29: Other long-term liabilities | B29: 3330 | C29: 3546 | D29: 5330 | E29: 8153 | F29: 10495 | G29: Other liabilities
A30: Total liabilities | B30: 28418 | C30: 30548 | D30: 36440 | E30: 43009 | F30: 48390
A32: Redeemable noncontrolling interests in subsidiaries | B32: 604 | C32: 568 | D32: 409 | E32: 242 | F32: 63 | G32: Noncontrolling interests
A33: Convertible senior notes | B33: 51 | C33: 0 | D33: 0 | E33: 0 | F33: 0 | G33: Debt
A35: Equity
A36: Preferred stock | B36: 0 | C36: 0 | D36: 0 | E36: 0 | F36: 0
A37: Common stock | B37: 1 | C37: 1 | D37: 3 | E37: 3 | F37: 3 | G37: Paid in capital
A38: Additional paid-in capital | B38: 27260 | C38: 29803 | D38: 32177 | E38: 34892 | F38: 38371 | G38: Paid in capital
A39: Accumulated other comprehensive loss | B39: 363 | C39: 54 | D39: -361 | E39: -143 | F39: -670 | G39: Other equity
A40: Retained earnings | B40: -5399 | C40: 331 | D40: 12885 | E40: 27882 | F40: 35209 | G40: Retained earnings
A41: Total stockholders’ equity | B41: 22225 | C41: 30189 | D41: 44705 | E41: 62634 | F41: 72913
A42: Noncontrolling interests in subsidiaries | B42: 850 | C42: 826 | D42: 785 | E42: 733 | F42: 704 | G42: Noncontrolling interests
A43: Total liabilities and equity | B43: 52148 | C43: 62131 | D43: 82338 | E43: 106618 | F43: 122070
A44: check | B44: =B19-B43 -> 0 | C44: =C19-C43 -> 0 | D44: =D19-D43 -> 0 | E44: =E19-E43 -> 0 | F44: =F19-F43 -> 0
A46: INCOME STATEMENT | G46: BUCKET | J46: 2020 | K46: 2021 | L46: 2022 | M46: 2023 | N46: 2024
A47: Revenues | I47: Revenues | J47: =SUM(B48:B50)+SUM(B52:B53) -> 31536 | K47: =SUM(C48:C50)+SUM(C52:C53) -> 53823 | L47: =SUM(D48:D50)+SUM(D52:D53) -> 81462 | M47: =SUM(E48:E50)+SUM(E52:E53) -> 96773 | N47: =SUM(F48:F50)+SUM(F52:F53) -> 97690
A48: Automotive sales | B48: 24604 | C48: 44125 | D48: 67210 | E48: 78509 | F48: 72480 | I48: Cost of goods sold | J48: =SUM(B56:B57)+SUM(B59:B60)-J53 -> 22584 | K48: =SUM(C56:C57)+SUM(C59:C60)-K53 -> 37306 | L48: =SUM(D56:D57)+SUM(D59:D60)-L53 -> 56862 | M48: =SUM(E56:E57)+SUM(E59:E60)-M53 -> 74446 | N48: =SUM(F56:F57)+SUM(F59:F60)-N53 -> 74872
A49: Automotive regulatory credits | B49: 1580 | C49: 1465 | D49: 1776 | E49: 1790 | F49: 2763 | I49: Gross profit | J49: =J47-J48 -> 8952 | K49: =K47-K48 -> 16517 | L49: =L47-L48 -> 24600 | M49: =M47-M48 -> 22327 | N49: =N47-N48 -> 22818
A50: Automotive leasing | B50: 1052 | C50: 1642 | D50: 2476 | E50: 2120 | F50: 1827 | I50: R&D | J50: =B64 -> 1491 | K50: =C64 -> 2593 | L50: =D64 -> 3075 | M50: =E64 -> 3969 | N50: =F64 -> 4540
A51: Total automotive revenues | B51: 27236 | C51: 47232 | D51: 71462 | E51: 82419 | F51: 77070 | I51: SG&A | J51: =B65 -> 3145 | K51: =C65 -> 4517 | L51: =D65 -> 3946 | M51: =E65 -> 4800 | N51: =F65 -> 5150
A52: Energy generation and storage | B52: 1994 | C52: 2789 | D52: 3909 | E52: 6035 | F52: 10086 | I52: EBITDA | J52: =J49-J50-J51 -> 4316 | K52: =K49-K50-K51 -> 9407 | L52: =L49-L50-L51 -> 17579 | M52: =M49-M50-M51 -> 13558 | N52: =N49-N50-N51 -> 13128
A53: Services and other | B53: 2306 | C53: 3802 | D53: 6091 | E53: 8319 | F53: 10534 | I53: D&A | J53: =B89 -> 2322 | K53: =C89 -> 2911 | L53: =D89 -> 3747 | M53: =E89 -> 4667 | N53: =F89 -> 5368
A54: Total revenues | B54: 31536 | C54: 53823 | D54: 81462 | E54: 96773 | F54: 97690 | G54: Revenues | I54: Other Opex | J54: =B66 -> 0 | K54: =C66 -> -27 | L54: =D66 -> 176 | M54: =E66 -> 0 | N54: =F66 -> 684
A55: Cost of revenues | I55: Operating Income | J55: =J52-J53-J54 -> 1994 | K55: =K52-K53-K54 -> 6523 | L55: =L52-L53-L54 -> 13656 | M55: =M52-M53-M54 -> 8891 | N55: =N52-N53-N54 -> 7076
A56: Automotive sales | B56: 19696 | C56: 32415 | D56: 49599 | E56: 65121 | F56: 61870 | I56: Interest income | J56: =B69 -> 30 | K56: =C69 -> 56 | L56: =D69 -> 297 | M56: =E69 -> 1066 | N56: =F69 -> 1569
A57: Automotive leasing | B57: 563 | C57: 978 | D57: 1509 | E57: 1268 | F57: 1003 | I57: Interest expense | J57: =B70 -> -748 | K57: =C70 -> -371 | L57: =D70 -> -191 | M57: =E70 -> -156 | N57: =F70 -> -350
A58: Total automotive cost of revenues | B58: 20259 | C58: 33393 | D58: 51108 | E58: 66389 | F58: 62873 | I58: Other | J58: =B71 -> -122 | K58: =C71 -> 135 | L58: =D71 -> -43 | M58: =E71 -> 172 | N58: =F71 -> 695
A59: Energy generation and storage | B59: 1976 | C59: 2918 | D59: 3621 | E59: 4894 | F59: 7446 | I59: Pre-Tax Income | J59: =SUM(J55:J58) -> 1154 | K59: =SUM(K55:K58) -> 6343 | L59: =SUM(L55:L58) -> 13719 | M59: =SUM(M55:M58) -> 9973 | N59: =SUM(N55:N58) -> 8990
A60: Services and other | B60: 2671 | C60: 3906 | D60: 5880 | E60: 7830 | F60: 9921 | I60: Taxes | J60: =B73 -> 292 | K60: =C73 -> 699 | L60: =D73 -> 1132 | M60: =E73 -> -5001 | N60: =F73 -> 1837
A61: Total cost of revenues | B61: 24906 | C61: 40217 | D61: 60609 | E61: 79113 | F61: 80240 | G61: Cost of goods sold | I61: Net Income | J61: =J59-J60 -> 862 | K61: =K59-K60 -> 5644 | L61: =L59-L60 -> 12587 | M61: =M59-M60 -> 14974 | N61: =N59-N60 -> 7153
A62: Gross profit | B62: 6630 | C62: 13606 | D62: 20853 | E62: 17660 | F62: 17450
A63: Operating expenses
A64: Research and development | B64: 1491 | C64: 2593 | D64: 3075 | E64: 3969 | F64: 4540 | G64: R&D
A65: Selling, general and administrative | B65: 3145 | C65: 4517 | D65: 3946 | E65: 4800 | F65: 5150 | G65: SG&A
A66: Restructuring and other | B66: 0 | C66: -27 | D66: 176 | E66: 0 | F66: 684 | G66: Other Opex
A67: Total operating expenses | B67: 4636 | C67: 7083 | D67: 7197 | E67: 8769 | F67: 10374
A68: Income from operations | B68: 1994 | C68: 6523 | D68: 13656 | E68: 8891 | F68: 7076
A69: Interest income | B69: 30 | C69: 56 | D69: 297 | E69: 1066 | F69: 1569 | G69: Interest income
A70: Interest expense | B70: -748 | C70: -371 | D70: -191 | E70: -156 | F70: -350 | G70: Interest expense
A71: Other income (expense), net | B71: -122 | C71: 135 | D71: -43 | E71: 172 | F71: 695 | G71: Other
A72: Income before income taxes | B72: 1154 | C72: 6343 | D72: 13719 | E72: 9973 | F72: 8990
A73: Provision for (benefit from) income taxes | B73: 292 | C73: 699 | D73: 1132 | E73: -5001 | F73: 1837 | G73: Taxes
A74: Net income | B74: 862 | C74: 5644 | D74: 12587 | E74: 14974 | F74: 7153
A75: Net income (loss) attributable to noncontrolling interests | B75: 141 | C75: 125 | D75: 31 | E75: -23 | F75: 62
A76: Net income attributable to common stockholders | B76: 721 | C76: 5519 | D76: 12556 | E76: 14997 | F76: 7091
A78: Net income per share of common stock attributable to common stockholders
A79: Basic | B79: 0.74 | C79: 5.6 | D79: 4.02 | E79: 4.73 | F79: 2.23
A80: Diluted | B80: 0.64 | C80: 4.9 | D80: 3.62 | E80: 4.30 | F80: 2.04
A81: Weighted average shares used in computing net income per share of common stock
A82: Basic | B82: 933 | C82: 986 | D82: 3130 | E82: 3174 | F82: 3197
A83: Diluted | B83: 1083 | C83: 1129 | D83: 3475 | E83: 3485 | F83: 3498
A85: CASH FLOW STATEMENT | G85: BUCKET | J85: 2020 | K85: 2021 | L85: 2022 | M85: 2023 | N85: 2024
A86: Cash Flows from Operating Activities | I86: Net income | J86: =B87 -> 862 | K86: =C87 -> 5644 | L86: =D87 -> 12587 | M86: =E87 -> 14974 | N86: =F87 -> 7153
A87: Net income | B87: 862 | C87: 5644 | D87: 12587 | E87: 14974 | F87: 7153 | G87: Net income | I87: D&A | J87: =B89 -> 2322 | K87: =C89 -> 2911 | L87: =D89 -> 3747 | M87: =E89 -> 4667 | N87: =F89 -> 5368
A88: Adjustments to reconcile net income to net cash provided by operating activities: | I88: Other non-cash charges | J88: =SUM(B90:B95) -> 2575 | K88: =SUM(C90:C95) -> 2424 | L88: =SUM(D90:D95) -> 2102 | M88: =SUM(E90:E95) -> -4137 | N88: =SUM(F90:F95) -> 2321
A89: Depreciation, amortization and impairment | B89: 2322 | C89: 2911 | D89: 3747 | E89: 4667 | F89: 5368 | G89: D&A | I89: 𝚫 in Accounts Receivables | J89: =B97 -> -652 | K89: =C97 -> -130 | L89: =D97 -> -1124 | M89: =E97 -> -586 | N89: =F97 -> -1083
A90: Stock-based compensation | B90: 1734 | C90: 2121 | D90: 1560 | E90: 1812 | F90: 1999 | G90: Other non-cash charges | I90: 𝚫 in Inventory | J90: =B98 -> -422 | K90: =C98 -> -1709 | L90: =D98 -> -6465 | M90: =E98 -> -1195 | N90: =F98 -> 937
A91: Inventory and purchase commitments write-downs | B91: 202 | C91: 140 | D91: 177 | E91: 463 | F91: 335 | G91: Other non-cash charges | I91: 𝚫 in Prepaid expenses | J91: =B100 -> -595 | K91: =C100 -> -1562 | L91: =D100 -> -3713 | M91: =E100 -> -2652 | N91: =F100 -> -3273
A92: Foreign currency transaction net unrealized (gain) loss | B92: 114 | C92: -55 | D92: 81 | E92: -144 | F92: -73 | G92: Other non-cash charges | I92: 𝚫 in A/P & Accrued Liabilities | J92: =B101 -> 2604 | K92: =C101 -> 5240 | L92: =D101 -> 8029 | M92: =E101 -> 2605 | N92: =F101 -> 3588
A93: Deferred income taxes | D93: -196 | E93: -6349 | F93: 477 | G93: Other non-cash charges | I93: Other Changes in OWC | J93: =B99+B102 -> -751 | K93: =C99+C102 -> -1321 | L93: =D99+D102 -> -439 | M93: =E99+E102 -> -420 | N93: =F99+F102 -> -88
A94: Non-cash interest and other operating activities | B94: 525 | C94: 245 | D94: 340 | E94: 81 | F94: 172 | G94: Other non-cash charges | I94: Net cash from operations | J94: =SUM(J86:J93) -> 5943 | K94: =SUM(K86:K93) -> 11497 | L94: =SUM(L86:L93) -> 14724 | M94: =SUM(M86:M93) -> 13256 | N94: =SUM(N86:N93) -> 14923
A95: Digital assets (gain) loss, net | B95: 0 | C95: -27 | D95: 140 | E95: 0 | F95: -589 | G95: Other non-cash charges
A96: Changes in operating assets and liabilities: | I96: Capex | J96: =B106 -> -3157 | K96: =C106 -> -6482 | L96: =D106 -> -7158 | M96: =E106 -> -8898 | N96: =F106 -> -11339
A97: Accounts receivable | B97: -652 | C97: -130 | D97: -1124 | E97: -586 | F97: -1083 | G97: 𝚫 in Accounts Receivables | I97: Other cash from investing | J97: =SUM(B107:B114) -> 25 | K97: =SUM(C107:C114) -> -1386 | L97: =SUM(D107:D114) -> -4815 | M97: =SUM(E107:E114) -> -6686 | N97: =SUM(F107:F114) -> -7448
A98: Inventory | B98: -422 | C98: -1709 | D98: -6465 | E98: -1195 | F98: 937 | G98: 𝚫 in Inventory | I98: Net cash from investing | J98: =SUM(J96:J97) -> -3132 | K98: =SUM(K96:K97) -> -7868 | L98: =SUM(L96:L97) -> -11973 | M98: =SUM(M96:M97) -> -15584 | N98: =SUM(N96:N97) -> -18787
A99: Operating lease vehicles | B99: -1072 | C99: -2114 | D99: -1570 | E99: -1952 | F99: -590 | G99: Other Changes in OWC
A100: Prepaid expenses and other assets | B100: =-251-344 -> -595 | C100: =-271-1291 -> -1562 | D100: -3713 | E100: -2652 | F100: -3273 | G100: 𝚫 in Prepaid expenses | I100: Equity issuance | J100: =B118 -> 12269 | K100: =C118 -> 0 | L100: =D118 -> 0 | M100: =E118 -> 0 | N100: =F118 -> 0
A101: Accounts payable, accrued and other liabilities | B101: =2102+7+495 -> 2604 | C101: =4578+186+476 -> 5240 | D101: 8029 | E101: 2605 | F101: 3588 | G101: 𝚫 in A/P & Accrued Liabilities | I101: Debt issuance | J101: =B119 -> 9713 | K101: =C119 -> 8883 | L101: =D119 -> 0 | M101: =E119 -> 3931 | N101: =F119 -> 5744
A102: Deferred revenue | B102: 321 | C102: 793 | D102: 1131 | E102: 1532 | F102: 502 | G102: Other Changes in OWC | I102: Debt repayment | J102: =B120+B122 -> -12201 | K102: =C120+C122 -> -14615 | L102: =D120+D122 -> -3866 | M102: =E120+E122 -> -1815 | N102: =F120+F122 -> -2881
A103: Net cash provided by operating activities | B103: 5943 | C103: 11497 | D103: 14724 | E103: =SUM(E87:E102) -> 13256 | F103: =SUM(F87:F102) -> 14923 | I103: Other cash from financing | J103: =B121+SUM(B123:B125) -> 192 | K103: =C121+SUM(C123:C125) -> 529 | L103: =D121+SUM(D123:D125) -> 339 | M103: =E121+SUM(E123:E125) -> 473 | N103: =F121+SUM(F123:F125) -> 990
I104: Net cash from financing | J104: =SUM(J100:J103) -> 9973 | K104: =SUM(K100:K103) -> -5203 | L104: =SUM(L100:L103) -> -3527 | M104: =SUM(M100:M103) -> 2589 | N104: =SUM(N100:N103) -> 3853
A105: Cash Flows from Investing Activities
...

Sheet 3-Statement Model_v1
B1: Historical | G1: Forecast
B2: 2020 | C2: 2021 | D2: 2022 | E2: 2023 | F2: 2024 | G2: 2025 | H2: 2026 | I2: 2027 | J2: 2028 | K2: 2029
A3: =IF(L32=0,"OK","NOT BALANCED") -> OK | B3: -5 | C3: -4 | D3: -3 | E3: -2 | F3: -1 | G3: 1 | H3: =G3+1 -> 2 | I3: =H3+1 -> 3 | J3: =I3+1 -> 4 | K3: =J3+1 -> 5
A4: ($ in millions) | F4: CASE: | G4: 2 | H4: =CHOOSE(G4,"BEAR","BASE","BULL") -> BASE
A5: BALANCE SHEET
A6: Assets
A7: Cash and Cash Equivalents | B7: 19384 | C7: 17576 | D7: 16253 | E7: 16398 | F7: 16139 | G7: =G103 -> 17105.519 | H7: =H103 -> 17618.685 | I7: =I103 -> 18147.245 | J7: =J103 -> 18691.662 | K7: =K103 -> 19252.412
A8: EXCESS CASH | G8: =IF(G92>0,G92,0) -> 4585.4875 | H8: =IF(H92>0,H92,0) -> 4912.9895 | I8: =IF(I92>0,I92,0) -> 8962.5995 | J8: =IF(J92>0,J92,0) -> 13835.74 | K8: =IF(K92>0,K92,0) -> 19252.789
A9: Short-term Investments | B9: 0 | C9: 131 | D9: 5932 | E9: 12696 | F9: 20424 | G9: =G104 -> 15093.105 | H9: =H104 -> 15545.898 | I9: =I104 -> 16012.275 | J9: =J104 -> 16492.643 | K9: =K104 -> 16987.423
A10: Accounts Receivable, net | B10: 1886 | C10: 1913 | D10: 2952 | E10: 3508 | F10: 4418 | G10: =G105 -> 4125.4487 | H10: =H105 -> 4249.2122 | I10: =I105 -> 4376.6885 | J10: =J105 -> 4507.9892 | K10: =K105 -> 4643.2289
A11: Inventory | B11: 4101 | C11: 5757 | D11: 12839 | E11: 13626 | F11: 12017 | G11: =G106 -> 13961.122 | H11: =H106 -> 14379.956 | I11: =I106 -> 14811.354 | J11: =J106 -> 15255.695 | K11: =K106 -> 15713.366
A12: Prepaid Expenses | B12: 1346 | C12: 1723 | D12: 2941 | E12: 3388 | F12: 5362 | G12: =G107 -> 4024.828 | H12: =H107 -> 4145.5728 | I12: =I107 -> 4269.94 | J12: =J107 -> 4398.0382 | K12: =K107 -> 4529.9794
A13: PP&E, net | B13: 12747 | C13: 18884 | D13: 23548 | E13: 29725 | F13: 35836 | G13: =G37 -> 40363.931 | H13: =H37 -> 45027.701 | I13: =I37 -> 49831.383 | J13: =J37 -> 54779.176 | K13: =K37 -> 59875.403
A14: Goodwill | B14: 207 | C14: 200 | D14: 194 | E14: 253 | F14: 244 | G14: 244 | H14: 244 | I14: 244 | J14: 244 | K14: 244
A15: Other Assets | B15: 12477 | C15: 15947 | D15: 17679 | E15: 27024 | F15: 27630 | G15: =F15 -> 27630 | H15: =G15 -> 27630 | I15: =H15 -> 27630 | J15: =I15 -> 27630 | K15: =J15 -> 27630
A16: Total Assets | B16: 52148 | C16: 62131 | D16: 82338 | E16: 106618 | F16: 122070 | G16: =SUM(G7:G15) -> 127133.44 | H16: =SUM(H7:H15) -> 133754.01 | I16: =SUM(I7:I15) -> 144285.49 | J16: =SUM(J7:J15) -> 155834.94 | K16: =SUM(K7:K15) -> 168128.6
A18: Liabilities
A19: A/P & Accrued Liabilities | B19: 10658 | C19: 16669 | D19: 23460 | E19: 23511 | F19: 23197 | G19: =G109 -> 23394.313 | H19: =H109 -> 24096.142 | I19: =I109 -> 24819.026 | J19: =J109 -> 25563.597 | K19: =K109 -> 26330.505
A20: Deferred Revenue | B20: 1458 | C20: 1447 | D20: 1747 | E20: 2864 | F20: 3168 | G20: =G110 -> 3018.621 | H20: =H110 -> 3109.1796 | I20: =I110 -> 3202.455 | J20: =J110 -> 3298.5287 | K20: =K110 -> 3397.4845
A21: NEW Revolver | G21: =-IF(G92<0,G92,0) -> 0 | H21: =-IF(H92<0,H92,0) -> 0 | I21: =-IF(I92<0,I92,0) -> 0 | J21: =-IF(J92<0,J92,0) -> 0 | K21: =-IF(K92<0,K92,0) -> 0
A22: Debt | B22: 11739 | C22: 6834 | D22: 3099 | E22: 5230 | F22: 8213 | G22: =G113 -> 5860 | H22: =H113 -> 1744 | I22: =I113 -> 1045 | J22: =J113 -> 802 | K22: =K113 -> 707
A23: Other Liabilities | B23: 4614 | C23: 5598 | D23: 8134 | E23: 11404 | F23: 13812 | G23: =G111 -> 12225.415 | H23: =H111 -> 12592.178 | I23: =I111 -> 12969.943 | J23: =J111 -> 13359.041 | K23: =K111 -> 13759.812
A24: Total Liabilities | B24: =SUM(B19:B23) -> 28469 | C24: =SUM(C19:C23) -> 30548 | D24: =SUM(D19:D23) -> 36440 | E24: =SUM(E19:E23) -> 43009 | F24: =SUM(F19:F23) -> 48390 | G24: =SUM(G19:G23) -> 44498.349 | H24: =SUM(H19:H23) -> 41541.499 | I24: =SUM(I19:I23) -> 42036.424 | ... K24: =SUM(K19:K23) -> 44194.802
A25: Shareholder's Equity
A26: Paid-in Capital | B26: 27261 | C26: 29804 | D26: 32180 | E26: 34895 | F26: 38374 | G26: =F26 -> 38374 | H26: =G26 -> 38374 | I26: =H26 -> 38374 | J26: =I26 -> 38374 | K26: =J26 -> 38374
A27: Other Equity | B27: 363 | C27: 54 | D27: -361 | E27: -143 | F27: -670 | G27: =F27 -> -670 | H27: =G27 -> -670 | I27: =H27 -> -670 | J27: =I27 -> -670 | K27: =J27 -> -670
A28: Retained Earnings | B28: -5399 | C28: 331 | D28: 12885 | E28: 27882 | F28: 35209 | G28: =G59 -> 44164.093 | H28: =H59 -> 53741.515 | I28: =I59 -> 63778.062 | J28: =J59 -> 74340.777 | K28: =K59 -> 85462.8
A29: Noncontrolling Interests | B29: 1454 | C29: 1394 | D29: 1194 | E29: 975 | F29: 767 | G29: =F29 -> 767 | H29: =G29 -> 767 | I29: =H29 -> 767 | J29: =I29 -> 767 | K29: =J29 -> 767
A30: Shareholder's Equity | B30: =SUM(B26:B29) -> 23679 | C30: =SUM(C26:C29) -> 31583 | D30: =SUM(D26:D29) -> 45898 | E30: =SUM(E26:E29) -> 63609 | F30: =SUM(F26:F29) -> 73680 | G30: =SUM(G26:G29) -> 82635.093 | H30: =SUM(H26:H29) -> 92212.515 | I30: =SUM(I26:I29) -> 102249.06 | ... K30: =SUM(K26:K29) -> 123933.8
A31: Total Liabilities and Shareholder's Equity | B31: =B24+B30 -> 52148 | C31: =C24+C30 -> 62131 | D31: =D24+D30 -> 82338 | E31: =E24+E30 -> 106618 | F31: =F24+F30 -> 122070 | G31: =G24+G30 -> 127133.44 | H31: =H24+H30 -> 133754.01 | I31: =I24+I30 -> 144285.49 | ... K31: =K24+K30 -> 168128.6
A32: Check | B32: 0 | C32: 0 | D32: 0 | E32: 0 | F32: 0 | G32: =G16-G31 -> 0 | H32: =H16-H31 -> 0 | I32: =I16-I31 -> 0 | J32: =J16-J31 -> 0 | K32: =K16-K31 -> 0 | L32: =SUM(B32:K32) -> 0
A34: Beginning PP&E | G34: =F37 -> 35836 | H34: =G37 -> 40363.931 | I34: =H37 -> 45027.701 | J34: =I37 -> 49831.383 | K34: =J37 -> 54779.176
A35: + Capex | G35: =+G114 -> 10062.07 | H35: =+H114 -> 10363.932 | I35: =+I114 -> 10674.85 | J35: =+J114 -> 10995.096 | K35: =+K114 -> 11324.948
A36: - D&A | G36: =G97 -> 5534.1385 | H36: =H97 -> 5700.1627 | I36: =I97 -> 5871.1675 | J36: =J97 -> 6047.3026 | K36: =K97 -> 6228.7216
A37: Ending PP&E | F37: =F13 -> 35836 | G37: =G34+G35-G36 -> 40363.931 | H37: =H34+H35-H36 -> 45027.701 | I37: =I34+I35-I36 -> 49831.383 | J37: =J34+J35-J36 -> 54779.176 | K37: =K34+K35-K36 -> 59875.403
A39: INCOME STATEMENT
A40: Revenues | B40: 31536 | C40: 53823 | D40: 81462 | E40: 96773 | F40: 97690 | G40: =G95 -> 100620.7 | H40: =H95 -> 103639.32 | I40: =I95 -> 106748.5 | J40: =J95 -> 109950.96 | K40: =K95 -> 113249.48
A41: Cost of Goods Sold | B41: 22584 | C41: 37306 | D41: 56862 | E41: 74446 | F41: 74872 | G41: =G96 -> 75465.525 | H41: =H96 -> 77729.491 | I41: =I96 -> 80061.375 | J41: =J96 -> 82463.217 | K41: =K96 -> 84937.113
A42: Gross profit | B42: 8952 | C42: 16517 | D42: 24600 | E42: 22327 | F42: 22818 | G42: =G40-G41 -> 25155.175 | H42: =H40-H41 -> 25909.83 | I42: =I40-I41 -> 26687.125 | J42: =J40-J41 -> 27487.739 | K42: =K40-K41 -> 28312.371
A43: R&D | B43: 1491 | C43: 2593 | D43: 3075 | E43: 3969 | F43: 4540 | G43: =G98 -> 4527.9315 | H43: =H98 -> 4663.7694 | I43: =I98 -> 4803.6825 | J43: =J98 -> 4947.793 | K43: =K98 -> 5096.2268
A44: SG&A | B44: 3145 | C44: 4517 | D44: 3946 | E44: 4800 | F44: 5150 | G44: =G99 -> 5031.035 | H44: =H99 -> 5181.966 | I44: =I99 -> 5337.425 | J44: =J99 -> 5497.5478 | K44: =K99 -> 5662.4742
A45: EBITDA | B45: 4316 | C45: 9407 | D45: 17579 | E45: 13558 | F45: 13128 | G45: =G42-G43-G44 -> 15596.209 | H45: =H42-H43-H44 -> 16064.095 | I45: =I42-I43-I44 -> 16546.018 | J45: =J42-J43-J44 -> 17042.398 | K45: =K42-K43-K44 -> 17553.67
A46: D&A | B46: 2322 | C46: 2911 | D46: 3747 | E46: 4667 | F46: 5368 | G46: =G97 -> 5534.1385 | H46: =H97 -> 5700.1627 | I46: =I97 -> 5871.1675 | J46: =J97 -> 6047.3026 | K46: =K97 -> 6228.7216
A47: Other Opex | B47: 0 | C47: -27 | D47: 176 | E47: 0 | F47: 684
A48: Operating Income | B48: 1994 | C48: 6523 | D48: 13656 | E48: 8891 | F48: 7076 | G48: =G45-G46-G47 -> 10062.07 | H48: =H45-H46-H47 -> 10363.932 | I48: =I45-I46-I47 -> 10674.85 | J48: =J45-J46-J47 -> 10995.096 | K48: =K45-K46-K47 -> 11324.948
A49: Interest Income | B49: 30 | C49: 56 | D49: 297 | E49: 1066 | F49: 1569 | G49: =G100 -> 968.34 | H49: =H100 -> 1301.4604 | I49: =I100 -> 1351.9004 | J49: =J100 -> 1626.5907 | K49: =K100 -> 1951.6441
A50: Interest Expense | B50: -748 | C50: -371 | D50: -191 | E50: -156 | F50: -350 | G50: =-G101 -> -369.585 | H50: =-H101 -> -263.7 | I50: =-I101 -> -78.48 | J50: =-J101 -> -47.025 | K50: =-K101 -> -36.09
A51: Other | B51: -122 | C51: 135 | D51: -43 | E51: 172 | F51: 695
A52: Pre-Tax Income | B52: 1154 | C52: 6343 | D52: 13719 | E52: 9973 | F52: 8990 | G52: =SUM(G48:G51) -> 10660.825 | H52: =SUM(H48:H51) -> 11401.692 | I52: =SUM(I48:I51) -> 11948.271 | J52: =SUM(J48:J51) -> 12574.661 | K52: =SUM(K48:K51) -> 13240.503
A53: Taxes | B53: 292 | C53: 699 | D53: 1132 | E53: -5001 | F53: 1837 | G53: =G124*G52 -> 1705.732 | H53: =H124*H52 -> 1824.2708 | I53: =I124*I52 -> 1911.7233 | J53: =J124*J52 -> 2011.9458 | K53: =K124*K52 -> 2118.4804
A54: Net Income | B54: 862 | C54: 5644 | D54: 12587 | E54: 14974 | F54: 7153 | G54: =G52-G53 -> 8955.093 | H54: =H52-H53 -> 9577.4217 | I54: =I52-I53 -> 10036.547 | J54: =J52-J53 -> 10562.715 | K54: =K52-K53 -> 11122.022
A56: Beginning Retained Earnings | G56: =F59 -> 35209 | H56: =G59 -> 44164.093 | I56: =H59 -> 53741.515 | J56: =I59 -> 63778.062 | K56: =J59 -> 74340.777
A57: + Net Income | G57: =G54 -> 8955.093 | H57: =H54 -> 9577.4217 | I57: =I54 -> 10036.547 | J57: =J54 -> 10562.715 | K57: =K54 -> 11122.022
A58: - Dividends | G58: 0 | H58: 0 | I58: 0 | J58: 0 | K58: 0
A59: Ending Retained Earnings | F59: =F28 -> 35209 | G59: =G56+G57-G58 -> 44164.093 | H59: =H56+H57-H58 -> 53741.515 | I59: =I56+I57-I58 -> 63778.062 | J59: =J56+J57-J58 -> 74340.777 | K59: =K56+K57-K58 -> 85462.8
A61: CASH FLOW STATEMENT
A62: Operating Cash Flow
A63: Net income | B63: 862 | C63: 5644 | D63: 12587 | E63: 14974 | F63: 7153 | G63: =G54 -> 8955.093 | H63: =H54 -> 9577.4217 | I63: =I54 -> 10036.547 | J63: =J54 -> 10562.715 | K63: =K54 -> 11122.022
A64: D&A | B64: 2322 | C64: 2911 | D64: 3747 | E64: 4667 | F64: 5368 | G64: =G97 -> 5534.1385 | H64: =H97 -> 5700.1627 | I64: =I97 -> 5871.1675 | J64: =J97 -> 6047.3026 | K64: =K97 -> 6228.7216
A65: Other non-cash charges | B65: 2575 | C65: 2424 | D65: 2102 | E65: -4137 | F65: 2321
A66: 𝚫 in Accounts Receivables | B66: -652 | C66: -130 | D66: -1124 | E66: -586 | F66: -1083 | G66: =-(G10-F10) -> 292.5513 | H66: =-(H10-G10) -> -123.76346 | I66: =-(I10-H10) -> -127.47636 | J66: =-(J10-I10) -> -131.30066 | K66: =-(K10-J10) -> -135.23968
A67: 𝚫 in Inventory | B67: -422 | C67: -1709 | D67: -6465 | E67: -1195 | F67: 937 | G67: =-(G11-F11) -> -1944.1221 | H67: =-(H11-G11) -> -418.83366 | I67: =-(I11-H11) -> -431.39867 | J67: =-(J11-I11) -> -444.34063 | K67: =-(K11-J11) -> -457.67085
A68: 𝚫 in Prepaid expenses | B68: -595 | C68: -1562 | D68: -3713 | E68: -2652 | F68: -3273 | G68: =-(G12-F12) -> 1337.172 | H68: =-(H12-G12) -> -120.74484 | I68: =-(I12-H12) -> -124.36719 | J68: =-(J12-I12) -> -128.0982 | K68: =-(K12-J12) -> -131.94115
A69: 𝚫 in A/P & Accrued Liabilities | B69: 2604 | C69: 5240 | D69: 8029 | E69: 2605 | F69: 3588 | G69: =G19-F19 -> 197.31275 | H69: =H19-G19 -> 701.82938 | I69: =I19-H19 -> 722.88426 | J69: =J19-I19 -> 744.57079 | K69: =K19-J19 -> 766.90792
A70: Other Changes in OWC | B70: -751 | C70: -1321 | D70: -439 | E70: -420 | F70: -88 | G70: =(G20-F20)+(G23-F23) -> -1735.9639 | H70: =(H20-G20)+(H23-G23) -> 457.32108 | I70: =(I20-H20)+(I23-H23) -> 471.04071 | J70: =(J20-I20)+(J23-I23) -> 485.17194 | K70: =(K20-J20)+(K23-J23) -> 499.72709
A71: Net cash from operations | B71: 5943 | C71: 11497 | D71: 14724 | E71: 13256 | F71: 14923 | G71: =SUM(G63:G70) -> 12636.181 | H71: =SUM(H63:H70) -> 15773.393 | I71: =SUM(I63:I70) -> 16418.398 | J71: =SUM(J63:J70) -> 17136.021 | K71: =SUM(K63:K70) -> 17892.527
A73: Investing Cash Flow
A74: Capex | B74: -3157 | C74: -6482 | D74: -7158 | E74: -8898 | F74: -11339 | G74: =-G114 -> -10062.07 | H74: =-H114 -> -10363.932 | I74: =-I114 -> -10674.85 | J74: =-J114 -> -10995.096 | K74: =-K114 -> -11324.948
A75: Other cash from investing | B75: 25 | C75: -1386 | D75: -4815 | E75: -6686 | F75: -7448 | G75: =-(G9-F9) -> 5330.895 | H75: =-(H9-G9) -> -452.79315 | I75: =-(I9-H9) -> -466.37694 | J75: =-(J9-I9) -> -480.36825 | K75: =-(K9-J9) -> -494.7793
A76: Net cash from investing | B76: -3132 | C76: -7868 | D76: -11973 | E76: -15584 | F76: -18787 | G76: =SUM(G74:G75) -> -4731.175 | H76: =SUM(H74:H75) -> -10816.725 | I76: =SUM(I74:I75) -> -11141.227 | J76: =SUM(J74:J75) -> -11475.464 | K76: =SUM(K74:K75) -> -11819.728
A78: Financing Cash Flow
A79: Equity issuance | B79: 12269 | C79: 0 | D79: 0 | E79: 0 | F79: 0
A80: Debt issuance | B80: 9713 | C80: 8883 | D80: 0 | E80: 3931 | F80: 5744
A81: Debt repayment | B81: -12201 | C81: -14615 | D81: -3866 | E81: -1815 | F81: -2881 | G81: =G22-F22 -> -2353 | H81: =H22-G22 -> -4116 | I81: =I22-H22 -> -699 | J81: =J22-I22 -> -243 | K81: =K22-J22 -> -95
A82: Other cash from financing | B82: 192 | C82: 529 | D82: 339 | E82: 473 | F82: 990
A83: Net cash from financing | B83: 9973 | C83: -5203 | D83: -3527 | E83: 2589 | F83: 3853 | G83: =SUM(G79:G82) -> -2353 | H83: =SUM(H79:H82) -> -4116 | I83: =SUM(I79:I82) -> -699 | J83: =SUM(J79:J82) -> -243 | K83: =SUM(K79:K82) -> -95
A84: FX impact | B84: 334 | C84: -183 | D84: -444 | E84: 4 | F84: -141
A86: Net change in cash for the period | B86: 13118 | C86: -1757 | D86: -1220 | E86: 265 | F86: -152 | G86: =G71+G76+G83 -> 5552.0065 | H86: =H71+H76+H83 -> 840.66759 | I86: =I71+I76+I83 -> 4578.1705 | J86: =J71+J76+J83 -> 5417.5574 | K86: =K71+K76+K83 -> 5977.7994
A88: Opening Cash | B88: 6783 | C88: 19901 | D88: 18144 | E88: 16924 | F88: 17189 | G88: =F90 -> 16139 | H88: =G90 -> 21691.006 | I88: =H90 -> 22531.674 | J88: =I90 -> 27109.845 | K88: =J90 -> 32527.402
A89: Net change in cash for the period | B89: 13118 | C89: -1757 | D89: -1220 | E89: 265 | F89: -152 | G89: =G86 -> 5552.0065 | H89: =H86 -> 840.66759 | I89: =I86 -> 4578.1705 | J89: =J86 -> 5417.5574 | K89: =K86 -> 5977.7994
A90: Closing Cash | B90: 19901 | C90: 18144 | D90: 16924 | E90: 17189 | F90: =F7 -> 16139 | G90: =SUM(G88:G89) -> 21691.006 | H90: =SUM(H88:H89) -> 22531.674 | I90: =SUM(I88:I89) -> 27109.845 | J90: =SUM(J88:J89) -> 32527.402 | K90: =SUM(K88:K89) -> 38505.201
A91: Required Cash | G91: =G7 -> 17105.519 | H91: =H7 -> 17618.685 | I91: =I7 -> 18147.245 | J91: =J7 -> 18691.662 | K91: =K7 -> 19252.412
A92: EXCESS Cash / (Revolver) | G92: =G90-G91 -> 4585.4875 | H92: =H90-H91 -> 4912.9895 | I92: =I90-I91 -> 8962.5995 | J92: =J90-J91 -> 13835.74 | K92: =K90-K91 -> 19252.789
A94: FORECASTED LINE ITEMS
A95: Revenues | B95: =B40 -> 31536 | C95: =C40 -> 53823 | D95: =D40 -> 81462 | E95: =E40 -> 96773 | F95: =F40 -> 97690 | G95: =F95*(1+G117) -> 100620.7 | H95: =G95*(1+H117) -> 103639.32 | I95: =H95*(1+I117) -> 106748.5 | J95: =I95*(1+J117) -> 109950.96 | K95: =J95*(1+K117) -> 113249.48
A96: Cost of goods sold | B96: =B41 -> 22584 | C96: =C41 -> 37306 | D96: =D41 -> 56862 | E96: =E41 -> 74446 | F96: =F41 -> 74872 | G96: =G118*G95 -> 75465.525 | H96: =H118*H95 -> 77729.491 | I96: =I118*I95 -> 80061.375 | J96: =J118*J95 -> 82463.217 | K96: =K118*K95 -> 84937.113
A97: D&A | B97: =B46 -> 2322 | C97: =C46 -> 2911 | D97: =D46 -> 3747 | E97: =E46 -> 4667 | F97: =F46 -> 5368 | G97: =G119*G95 -> 5534.1385 | H97: =H119*H95 -> 5700.1627 | I97: =I119*I95 -> 5871.1675 | J97: =J119*J95 -> 6047.3026 | K97: =K119*K95 -> 6228.7216
A98: R&D | B98: =B43 -> 1491 | C98: =C43 -> 2593 | D98: =D43 -> 3075 | E98: =E43 -> 3969 | F98: =F43 -> 4540 | G98: =G120*G95 -> 4527.9315 | H98: =H120*H95 -> 4663.7694 | I98: =I120*I95 -> 4803.6825 | J98: =J120*J95 -> 4947.793 | K98: =K120*K95 -> 5096.2268
A99: SG&A | B99: =B44 -> 3145 | C99: =C44 -> 4517 | D99: =D44 -> 3946 | E99: =E44 -> 4800 | F99: =F44 -> 5150 | G99: =G121*G95 -> 5031.035 | H99: =H121*H95 -> 5181.966 | I99: =I121*I95 -> 5337.425 | J99: =J121*J95 -> 5497.5478 | K99: =K121*K95 -> 5662.4742
A100: Interest income | B100: =B49 -> 30 | C100: =C49 -> 56 | D100: =D49 -> 297 | E100: =E49 -> 1066 | F100: =F49 -> 1569 | G100: =G122*SUM(F7:F8) -> 968.34 | H100: =H122*SUM(G7:G8) -> 1301.4604 | I100: =I122*SUM(H7:H8) -> 1351.9004 | J100: =J122*SUM(I7:I8) -> 1626.5907 | K100: =K122*SUM(J7:J8) -> 1951.6441
A101: Interest expense | B101: =-B50 -> 748 | C101: =-C50 -> 371 | D101: =-D50 -> 191 | E101: =-E50 -> 156 | F101: =-F50 -> 350 | G101: =G123*SUM(F112:F113) -> 369.585 | H101: =H123*SUM(G112:G113) -> 263.7 | I101: =I123*SUM(H112:H113) -> 78.48 | J101: =J123*SUM(I112:I113) -> 47.025 | K101: =K123*SUM(J112:J113) -> 36.09
A102: Taxes | B102: =B53 -> 292 | C102: =C53 -> 699 | D102: =D53 -> 1132 | E102: =E53 -> -5001 | F102: =F53 -> 1837 | G102: =G53 -> 1705.732 | H102: =H53 -> 1824.2708 | I102: =I53 -> 1911.7233 | ... K102: =K53 -> 2118.4804
A103: Required Cash | B103: =B7 -> 19384 | C103: =C7 -> 17576 | D103: =D7 -> 16253 | E103: =E7 -> 16398 | F103: =F7 -> 16139 | G103: =G95*G125 -> 17105.519 | H103: =H95*H125 -> 17618.685 | I103: =I95*I125 -> 18147.245 | J103: =J95*J125 -> 18691.662 | K103: =K95*K125 -> 19252.412
A104: Short-term investments | B104: =B9 -> 0 | C104: =C9 -> 131 | D104: =D9 -> 5932 | E104: =E9 -> 12696 | F104: =F9 -> 20424 | G104: =G95*G126 -> 15093.105 | H104: =H95*H126 -> 15545.898 | I104: =I95*I126 -> 16012.275 | J104: =J95*J126 -> 16492.643 | K104: =K95*K126 -> 16987.423
A105: Accounts receivable, net | B105: =B10 -> 1886 | C105: =C10 -> 1913 | D105: =D10 -> 2952 | E105: =E10 -> 3508 | F105: =F10 -> 4418 | G105: =G127*G95 -> 4125.4487 | H105: =H127*H95 -> 4249.2122 | I105: =I127*I95 -> 4376.6885 | J105: =J127*J95 -> 4507.9892 | K105: =K127*K95 -> 4643.2289
A106: Inventory | B106: =B11 -> 4101 | C106: =C11 -> 5757 | D106: =D11 -> 12839 | E106: =E11 -> 13626 | F106: =F11 -> 12017 | G106: =G128*G96 -> 13961.122 | H106: =H128*H96 -> 14379.956 | I106: =I128*I96 -> 14811.354 | J106: =J128*J96 -> 15255.695 | K106: =K128*K96 -> 15713.366
A107: Prepaid expenses | B107: =B12 -> 1346 | C107: =C12 -> 1723 | D107: =D12 -> 2941 | E107: =E12 -> 3388 | F107: =F12 -> 5362 | G107: =G129*G95 -> 4024.828 | H107: =H129*H95 -> 4145.5728 | I107: =I129*I95 -> 4269.94 | J107: =J129*J95 -> 4398.0382 | K107: =K129*K95 -> 4529.9794
A108: Other assets | B108: =B15 -> 12477 | C108: =C15 -> 15947 | D108: =D15 -> 17679 | E108: =E15 -> 27024 | F108: =F15 -> 27630 | G108: =G95*G130 -> 26161.382 | H108: =H95*H130 -> 26946.223 | I108: =I95*I130 -> 27754.61 | J108: =J95*J130 -> 28587.248 | K108: =K95*K130 -> 29444.866
A109: A/P & Accrued Liabilities | B109: =B19 -> 10658 | C109: =C19 -> 16669 | D109: =D19 -> 23460 | E109: =E19 -> 23511 | F109: =F19 -> 23197 | G109: =G131*G96 -> 23394.313 | H109: =H131*H96 -> 24096.142 | I109: =I131*I96 -> 24819.026 | J109: =J131*J96 -> 25563.597 | K109: =K131*K96 -> 26330.505
A110: Deferred Revenue | B110: =B20 -> 1458 | C110: =C20 -> 1447 | D110: =D20 -> 1747 | E110: =E20 -> 2864 | F110: =F20 -> 3168 | G110: =G95*G132 -> 3018.621 | H110: =H95*H132 -> 3109.1796 | I110: =I95*I132 -> 3202.455 | J110: =J95*J132 -> 3298.5287 | K110: =K95*K132 -> 3397.4845
...
